{
  "intents": [
    {
      "tag": "greeting",
      "patterns": [
        "Hi",
        "How are you",
        "Is anyone there?",
        "Hello",
        "Good day",
        "Whats up"
      ],
      "responses": [
        "Hello!",
        "Hi there, how can I help?",
        "nice to meet you",
        "hello there , how can i help"
      ],
      "context_set": [""]
    },
    {
      "tag": "goodbye",
      "patterns": [
        "see ya",
        "See you later",
        "Goodbye",
        "I am Leaving",
        "Have a Good day",
        "bye"
      ],
      "responses": ["Sad to see you go :(", "Talk to you later", "Goodbye!"],
      "context_set": [""]
    },
    {
      "tag": "name",
      "patterns": [
        "what is your name",
        "whats your name?"
      ],
      "responses": ["I'm library  BOT!", "I'm library BOT."],
      "context_set": [""]
    },
    {
      "tag": "hours",
      "patterns": [
        "when is library open",
        "what are the working hours",
        "hours of operation",
        "operating hours",
        "what are the working hours of library"
      ],
      "responses": ["We are open 9am to 5pm College hours!"],
      "context_set": [""]
    },
    {
        "tag": "where is library ",
        "patterns": [
            "where is library",
            "library location",
            "location of library",
            "where can i find library",
            "where i can find the library"
        ],
        "responses": [
            ""
        ],
        "context_set": [
            ""
        ]
    },
    {
        "tag": "are books arrange according to departments",
        "patterns": [
            "are books arrange according to departments",
            "can we browse the books according departments",
            "can we search the books according to departments"
        ],
        "responses": [
            ""
        ],
        "context_set": [
            ""
        ]
    },
    {
        "tag": "where can i find library",
        "patterns": [
            "where can i find library",
            "where is library",
            "library location",
            "location of library",
            "where can i find library"
        ],
        "responses": [
            ""
        ],
        "context_set": [
            ""
        ]
    },
    {
        "tag": "room number of library",
        "patterns": [
            "room number of library",
            "where can i find library",
            "where is library",
            "library location",
            "location of library"
        ],
        "responses": [
            ""
        ],
        "context_set": [
            ""
        ]
    },
    {
        "tag": "where is library located",
        "patterns": [
            "where is library located",
            "room number of library",
            "where can i find library",
            "where is library",
            "library location"
            
        ],
        "responses": [
            ""
        ],
        "context_set": [
            ""
        ]
    },
    {
        "tag": "UCEN Library",
        "patterns": [
            "UCEN Library",
            "library UCEN",
            "library of UCEN"
        ],
        "responses": [
            ""
        ],
        "context_set": [
            ""
        ]
    },
    {
        "tag": "who is library officer",
        "patterns": [
            "who is library officer",
            "who is the officer of library",
            "officer of library",
            "library officer"
        ],
        "responses": [
            ""
        ],
        "context_set": [
            ""
        ]
    },
    {
        "tag": "who is incharge of library",
        "patterns": [
            "who is incharge of library",
            "who is library officer",
            "who is the officer of library",
            "officer of library",
            "library officer"
        ],
        "responses": [
            ""
        ],
        "context_set": [
            ""
        ]
    },
    {
        "tag": "library officer",
        "patterns": [
            "library officer",
            "who is incharge of library",
            "who is library officer",
            "who is the officer of library",
            "officer of library"
        ],
        "responses": [
            ""
        ],
        "context_set": [
            ""
        ]
    },
    {
        "tag": "incharge of library",
        "patterns": [
            "incharge of library",
            "who is incharge of library",
            "who is library officer",
            "who is the officer of library",
            "officer of library"
        ],
        "responses": [
            ""
        ],
        "context_set": [
            ""
        ]
    },
    {
        "tag": "library hours",
        "patterns": [
            "library hours",
            "timing of library",
            "timing library",
            "library timings"
        ],
        "responses": [
            ""
        ],
        "context_set": [
            ""
        ]
    },
    {
        "tag": "what is the timing of library",
        "patterns": [
            "what is the timing of library",
            "library hours",
            "timing of library",
            "timing library",
            "library timings"
        ],
        "responses": [
            ""
        ],
        "context_set": [
            ""
        ]
    },
    {
        "tag": "library timings",
        "patterns": [
            "library timings",
            "what is the timing of library",
            "library hours",
            "timing of library",
            "timing library"
        ],
        "responses": [
            ""
        ],
        "context_set": [
            ""
        ]
    },
    {
        "tag": "how many text books are available",
        "patterns": [
            "number of text books",
            "how many text books are available",
            "number of text books available in library",
            "availability of library text books",
            "total number of availability of library text books"
        ],
        "responses": [
            ""
        ],
        "context_set": [
            ""
        ]
    },
    {
        "tag": "validity of books in days",
        "patterns": [
            "validity of books in days",
            "books validity",
            "book validity",
            "books time validity"
        ],
        "responses": [
            ""
        ],
        "context_set": [
            ""
        ]
    },
    {
        "tag": "number of text books",
        "patterns": [
            "number of text books",
            "how many text books are available",
            "number of text books available in library",
            "availability of library text books",
            "total number of availability of library text books"
        ],
        "responses": [
            ""
        ],
        "context_set": [
            ""
        ]
    },
    {
        "tag": "total number of text books in library",
        "patterns": [
            "total number of text books in library",
            "number of text books",
            "how many text books are available",
            "number of text books available in library",
            "availability of library text books"
        ],
        "responses": [
            ""
        ],
        "context_set": [
            ""
        ]
    },
    {
        "tag": "total number of books in civil department",
        "patterns": [
            "total number of books in civil department",
            "number of books in civil department",
            "total number of books in civil department",
            "number of books in civil department",
            "total number of books in civil department"
            
        ],
        "responses": [
            ""
        ],
        "context_set": [
            ""
        ]
    },
    {
        "tag": "number of books in civil department",
        "patterns": [
            "number of books in civil department",
            "total number of books in civil department",
            "number of books in civil department",
            "total number of books in civil department",
            "number of books in civil department"
        ],
        "responses": [
            ""
        ],
        "context_set": [
            ""
        ]
    },
    {
        "tag": "total number of books in CSE department",
        "patterns": [
            "total number of books in CSE department",
            "number of books in CSE department",
            "total number of books in CSE department",
            "number of books in CSE department",
            "total number of books in CSE department"
        ],
        "responses": [
            ""
        ],
        "context_set": [
            ""
        ]
    },
    {
        "tag": "number of books in CSE department",
        "patterns": [
            "number of books in CSE department",
            "total number of books in CSE department",
            "number of books in CSE department",
            "total number of books in CSE department",
            "number of books in CSE department"
            
        ],
        "responses": [
            ""
        ],
        "context_set": [
            ""
        ]
    },
    {
        "tag": "total number of books in Mechnical department",
        "patterns": [
            "total number of books in Mechnical department",
            "number of books in Mechanical department",
            "total number of books in Mechanical department",
            "number of books in Mechanical department",
            "number of books in Mechanical department"
        ],
        "responses": [
            ""
        ],
        "context_set": [
            ""
        ]
    },
    {
        "tag": "number of books in Mechanical department",
        "patterns": [
            "number of books in Mechanical department",
            "total number of books in Mechanical department",
            "number of books in Mechanical department",
            "number of books in Mechanical department",
            "total number of books in Mechanical department"
        ],
        "responses": [
            ""
        ],
        "context_set": [
            ""
        ]
    },
    {
        "tag": "total number of books in ECE department",
        "patterns": [
            "total number of books in ECE department",
            "number of books in ECE department",
            "number of books in ECE department",
            "total number of books in ECE department",
            "total number of books in ECE department"
        ],
        "responses": [
            ""
        ],
        "context_set": [
            ""
        ]
    },
    {
        "tag": "number of books in ECE department",
        "patterns": [
            "number of books in ECE department",
            "number of books in ECE department",
            "total number of books in ECE department",
            "total number of books in ECE department",
            "number of books in ECE department"
        ],
            
        "responses": [
            ""
        ],
        "context_set": [
            ""
        ]
    },
    {
        "tag": "number of books in EEE department",
        "patterns": [
            "number of books in EEE department",
            "total number of books in EEE department",
            "total number of books in EEE department",
            "number of books in EEE department",
            "how many books are available in EEE department"
        ],
        "responses": [
            ""
        ],
        "context_set": [
            ""
        ]
    },
    {
        "tag": "total number of books in EEE department",
        "patterns": [
            "total number of books in EEE department",
            "total number of books in EEE department",
            "number of books in EEE department",
            "how many books are available in EEE department",
            "total how many books are available in EEE departments"
        ],
        "responses": [
            ""
        ],
        "context_set": [
            ""
        ]
    },
    {
        "tag": "total number of books in IT department",
        
        
        "patterns": [
            "total number of books in IT department",
            "number of books in IT department",
            "how many books are available in IT department",
            "total how many books are available in IT departments"
        ],
        "responses": [
            ""
        ],
        "context_set": [
            ""
        ]
    },
    {
        "tag": "number of books in IT department",
        "patterns": [
            "number of books in IT department",
            "how many books are available in IT department",
            "total how many books are available in IT departments",
            "total number of IT books in library",
            "number of IT books in libarary"
        ],
        "responses": [
            ""
        ],
        "context_set": [
            ""
        ]
    }

  ]
}
